zoo_mcp/__init__.py
zoo_mcp/__main__.py
zoo_mcp/ai_tools.py
zoo_mcp/kcl_docs.py
zoo_mcp/kcl_samples.py
zoo_mcp/server.py
zoo_mcp/utils/__init__.py
zoo_mcp/utils/image_utils.py
zoo_mcp/zoo_tools.py
zoo_mcp-0.9.1.dist-info/licenses/LICENSE
zoo_mcp-0.9.1.dist-info/WHEEL
zoo_mcp-0.9.1.dist-info/entry_points.txt
zoo_mcp-0.9.1.dist-info/METADATA
zoo_mcp-0.9.1.dist-info/RECORD
