Metadata-Version: 2.4
Name: zoo_mcp
Version: 0.9.1
Summary: An MCP server utilizing Zoo's various tools
Keywords: zoo,mcp,kittycad,3d,modeling,server
Author: Ryan Barton
Author-email: Ryan Barton <ryan@zoo.dev>
License-Expression: MIT
License-File: LICENSE
Classifier: Development Status :: 4 - Beta
Classifier: Intended Audience :: Developers
Classifier: Topic :: Software Development
Classifier: Topic :: Scientific/Engineering :: Artificial Intelligence
Classifier: Programming Language :: Python :: 3
Classifier: Programming Language :: Python :: 3.11
Classifier: Programming Language :: Python :: 3.12
Classifier: Programming Language :: Python :: 3.13
Requires-Dist: aiofiles~=25.1
Requires-Dist: kittycad<=2.0
Requires-Dist: mcp[cli]>1.23.0,<2.0
Requires-Dist: pillow>=11.3,<13.0
Requires-Dist: truststore~=0.10
Requires-Dist: zoo-kcl>=0.3.117
Maintainer: Ryan Barton
Maintainer-email: Ryan Barton <ryan@zoo.dev>
Requires-Python: >=3.11, <3.14
Project-URL: Repository, https://github.com/KittyCAD/zoo-mcp
